minte/__init__.py
minte/cache.py
minte/controller.py
minte/emulator.py
minte/parser.py
minte/plotting.py
minte/py.typed
minte/web_controller.py
minte/data/itn_dn0.csv
minte/models/cases/args.json
minte/models/cases/gru_best.pt
minte/models/cases/lstm_best.pt
minte/models/cases/static_scaler.pkl
minte/models/prevalence/args.json
minte/models/prevalence/gru_best.pt
minte/models/prevalence/lstm_best.pt
minte/models/prevalence/static_scaler.pkl
minte-1.3.1.dist-info/METADATA
minte-1.3.1.dist-info/WHEEL
minte-1.3.1.dist-info/RECORD
