Metadata-Version: 2.4
Name: minte
Version: 1.3.1
Summary: Malaria Intervention Emulator (MINTe) - Neural network-based malaria scenario predictions
Project-URL: Homepage, https://github.com/CosmoNaught/minte
Project-URL: Documentation, https://github.com/CosmoNaught/minte#readme
Project-URL: Repository, https://github.com/CosmoNaught/minte
Project-URL: Issues, https://github.com/CosmoNaught/minte/issues
Author-email: Cosmo Santoni <cosmo.santoni@imperial.ac.uk>
License: MIT
Keywords: emulator,malaria,neural-network,public-health,simulation
Classifier: Development Status :: 4 - Beta
Classifier: Intended Audience :: Science/Research
Classifier: License :: OSI Approved :: MIT License
Classifier: Programming Language :: Python :: 3
Classifier: Programming Language :: Python :: 3.10
Classifier: Programming Language :: Python :: 3.11
Classifier: Programming Language :: Python :: 3.12
Classifier: Topic :: Scientific/Engineering :: Bio-Informatics
Requires-Python: >=3.10
Requires-Dist: estimint>=1.2.0
Requires-Dist: joblib>=1.3.0
Requires-Dist: matplotlib>=3.7.0
Requires-Dist: numpy>=1.24.0
Requires-Dist: pandas>=2.0.0
Requires-Dist: scikit-learn==1.6.1
Requires-Dist: scipy>=1.10.0
Requires-Dist: torch>=2.0.0
Provides-Extra: dev
Requires-Dist: black>=23.0.0; extra == 'dev'
Requires-Dist: mypy>=1.0.0; extra == 'dev'
Requires-Dist: pytest-cov>=4.0.0; extra == 'dev'
Requires-Dist: pytest>=7.0.0; extra == 'dev'
Requires-Dist: ruff>=0.1.0; extra == 'dev'
Provides-Extra: xgboost
Requires-Dist: xgboost>=2.0.0; extra == 'xgboost'
